{
    "sourceFile": "src/http/categorias.json",
    "activeCommit": 0,
    "commits": [
        {
            "activePatchIndex": 1,
            "patches": [
                {
                    "date": 1745414484676,
                    "content": "Index: \n===================================================================\n--- \n+++ \n"
                },
                {
                    "date": 1745414520810,
                    "content": "Index: \n===================================================================\n--- \n+++ \n@@ -1,176 +1,176 @@\n [\r\n   {\r\n-  \"nome\": \"Laticínios e Ovos\",\r\n-  \"ingredientes\": [\r\n-  \"Ovos\",\r\n-  \"Queijo\",\r\n-  \"Leite\",\r\n-  \"Manteiga\",\r\n-  \"Creme de Leite\",\r\n-  \"Iogurte\",\r\n-  \"Leite Condensado\",\r\n-  \"Sorvete\"\r\n-  ],\r\n-  \"imagem\": \"laticinios_e_ovos.png\"\r\n+    \"nome\": \"Laticínios e Ovos\",\r\n+    \"ingredientes\": [\r\n+      \"Ovos\",\r\n+      \"Queijo\",\r\n+      \"Leite\",\r\n+      \"Manteiga\",\r\n+      \"Creme de Leite\",\r\n+      \"Iogurte\",\r\n+      \"Leite Condensado\",\r\n+      \"Sorvete\"\r\n+    ],\r\n+    \"imagem\": \"laticinios_e_ovos.png\"\r\n   },\r\n   {\r\n-  \"nome\": \"Farinhas e Fermentos\",\r\n-  \"ingredientes\": [\r\n-  \"Farinha de trigo\",\r\n-  \"Polvilho\",\r\n-  \"Farinha de rosca\",\r\n-  \"Canjica\",\r\n-  \"Farinha de mandioca\",\r\n-  \"Fubá\",\r\n-  \"Linhaça\",\r\n-  \"Fermento químico\"\r\n-  ],\r\n-  \"imagem\": \"farinhas_e_fermentos.png\"\r\n+    \"nome\": \"Farinhas e Fermentos\",\r\n+    \"ingredientes\": [\r\n+      \"Farinha de trigo\",\r\n+      \"Polvilho\",\r\n+      \"Farinha de rosca\",\r\n+      \"Canjica\",\r\n+      \"Farinha de mandioca\",\r\n+      \"Fubá\",\r\n+      \"Linhaça\",\r\n+      \"Fermento químico\"\r\n+    ],\r\n+    \"imagem\": \"farinhas_e_fermentos.png\"\r\n   },\r\n   {\r\n-  \"nome\": \"Temperos e Especiarias\",\r\n-  \"ingredientes\": [\r\n-  \"Canela\",\r\n-  \"Cravo\",\r\n-  \"Orégano\",\r\n-  \"Noz moscada\",\r\n-  \"Tomilho\",\r\n-  \"Pimenta do Reino\",\r\n-  \"Cominho\"\r\n-  ],\r\n-  \"imagem\": \"temperos_e_especiarias.png\"\r\n+    \"nome\": \"Temperos e Especiarias\",\r\n+    \"ingredientes\": [\r\n+      \"Canela\",\r\n+      \"Cravo\",\r\n+      \"Orégano\",\r\n+      \"Noz moscada\",\r\n+      \"Tomilho\",\r\n+      \"Pimenta do Reino\",\r\n+      \"Cominho\"\r\n+    ],\r\n+    \"imagem\": \"temperos_e_especiarias.png\"\r\n   },\r\n   {\r\n-  \"nome\": \"Óleos, Gorduras e Vinagres\",\r\n-  \"ingredientes\": [\r\n-  \"Vinagre\",\r\n-  \"Óleo\",\r\n-  \"Dendê\",\r\n-  \"Azeite de Oliva\",\r\n-  \"Banha\",\r\n-  \"Aceto Balsâmico\",\r\n-  \"Óleo de coco\"\r\n-  ],\r\n-  \"imagem\": \"oleos_gorduras_e_vinagres.png\"\r\n+    \"nome\": \"Óleos, Gorduras e Vinagres\",\r\n+    \"ingredientes\": [\r\n+      \"Vinagre\",\r\n+      \"Óleo\",\r\n+      \"Dendê\",\r\n+      \"Azeite de Oliva\",\r\n+      \"Banha\",\r\n+      \"Aceto Balsâmico\",\r\n+      \"Óleo de coco\"\r\n+    ],\r\n+    \"imagem\": \"oleos_gorduras_e_vinagres.png\"\r\n   },\r\n   {\r\n-  \"nome\": \"Hortaliças e Verduras\",\r\n-  \"ingredientes\": [\r\n-  \"Cebola\",\r\n-  \"Alho\",\r\n-  \"Tomate\",\r\n-  \"Abóbora\",\r\n-  \"Abobrinha\",\r\n-  \"Batata\",\r\n-  \"Pimentão\",\r\n-  \"Espinafre\",\r\n-  \"Cenoura\"\r\n-  ],\r\n-  \"imagem\": \"hortalicas_e_verduras.png\"\r\n+    \"nome\": \"Hortaliças e Verduras\",\r\n+    \"ingredientes\": [\r\n+      \"Cebola\",\r\n+      \"Alho\",\r\n+      \"Tomate\",\r\n+      \"Abóbora\",\r\n+      \"Abobrinha\",\r\n+      \"Batata\",\r\n+      \"Pimentão\",\r\n+      \"Espinafre\",\r\n+      \"Cenoura\"\r\n+    ],\r\n+    \"imagem\": \"hortalicas_e_verduras.png\"\r\n   },\r\n   {\r\n-  \"nome\": \"Açúcares e Adoçantes\",\r\n-  \"ingredientes\": [\r\n-  \"Açúcar branco\",\r\n-  \"Açúcar mascavo\",\r\n-  \"Açúcar cristal\",\r\n-  \"Melado\",\r\n-  \"Mel\",\r\n-  \"Baunilha\",\r\n-  \"Glucose\",\r\n-  \"Xilito\",\r\n-  \"Stevia\"\r\n-  ],\r\n-  \"imagem\": \"acucares_e_adocantes.png\"\r\n+    \"nome\": \"Açúcares e Adoçantes\",\r\n+    \"ingredientes\": [\r\n+      \"Açúcar branco\",\r\n+      \"Açúcar mascavo\",\r\n+      \"Açúcar cristal\",\r\n+      \"Melado\",\r\n+      \"Mel\",\r\n+      \"Baunilha\",\r\n+      \"Glucose\",\r\n+      \"Xilito\",\r\n+      \"Stevia\"\r\n+    ],\r\n+    \"imagem\": \"acucares_e_adocantes.png\"\r\n   },\r\n   {\r\n-  \"nome\": \"Proteínas Animais\",\r\n-  \"ingredientes\": [\r\n-  \"Peixe\",\r\n-  \"Carne bovina\",\r\n-  \"Carne de porco\",\r\n-  \"Frango\",\r\n-  \"Bacon\",\r\n-  \"Salsicha\",\r\n-  \"Atum\",\r\n-  \"Salmão\",\r\n-  \"Presunto\",\r\n-  \"Bacalhau\"\r\n-  ],\r\n-  \"imagem\": \"proteinas_animais.png\"\r\n+    \"nome\": \"Proteínas Animais\",\r\n+    \"ingredientes\": [\r\n+      \"Peixe\",\r\n+      \"Carne bovina\",\r\n\\ No newline at end of file\n+      \"Carne de porco\",\r\n+      \"Frango\",\r\n+      \"Bacon\",\r\n+      \"Salsicha\",\r\n+      \"Atum\",\r\n+      \"Salmão\",\r\n+      \"Presunto\",\r\n+      \"Bacalhau\"\r\n+    ],\r\n+    \"imagem\": \"proteinas_animais.png\"\r\n   },\r\n   {\r\n-  \"nome\": \"Grãos, Cereais e Leguminosas\",\r\n-  \"ingredientes\": [\r\n-  \"Arroz\",\r\n-  \"Feijão\",\r\n-  \"Aveia\",\r\n-  \"Ervilha\",\r\n-  \"Lentilha\",\r\n-  \"Grão de bico\",\r\n-  \"Milho\",\r\n-  \"Gergelim\",\r\n-  \"Quinoa\"\r\n-  ],\r\n-  \"imagem\": \"graos_cerais_e_leguminosas.png\"\r\n+    \"nome\": \"Grãos, Cereais e Leguminosas\",\r\n+    \"ingredientes\": [\r\n+      \"Arroz\",\r\n+      \"Feijão\",\r\n+      \"Aveia\",\r\n+      \"Ervilha\",\r\n+      \"Lentilha\",\r\n+      \"Grão de bico\",\r\n+      \"Milho\",\r\n+      \"Gergelim\",\r\n+      \"Quinoa\"\r\n+    ],\r\n+    \"imagem\": \"graos_cerais_e_leguminosas.png\"\r\n   },\r\n   {\r\n-  \"nome\": \"Frutas frescas\",\r\n-  \"ingredientes\": [\r\n-  \"Banana\",\r\n-  \"Maçã\",\r\n-  \"Uva\",\r\n-  \"Pera\",\r\n-  \"Limão\",\r\n-  \"Morango\",\r\n-  \"Ameixa\",\r\n-  \"Framboesa\",\r\n-  \"Acabaxi\"\r\n-  ],\r\n-  \"imagem\": \"frutas_frescas.png\"\r\n+    \"nome\": \"Frutas frescas\",\r\n+    \"ingredientes\": [\r\n+      \"Banana\",\r\n+      \"Maçã\",\r\n+      \"Uva\",\r\n+      \"Pera\",\r\n+      \"Limão\",\r\n+      \"Morango\",\r\n+      \"Ameixa\",\r\n+      \"Framboesa\",\r\n+      \"Acabaxi\"\r\n+    ],\r\n+    \"imagem\": \"frutas_frescas.png\"\r\n   },\r\n   {\r\n-  \"nome\": \"Frutas secas\",\r\n-  \"ingredientes\": [\r\n-  \"Castanha de caju\",\r\n-  \"Castanha do pará\",\r\n-  \"Uva passa\",\r\n-  \"Damasco\",\r\n-  \"Tâmara\",\r\n-  \"Pistache\",\r\n-  \"Amêndoa\",\r\n-  \"Amendoim\"\r\n-  ],\r\n-  \"imagem\": \"frutas_secas.png\"\r\n+    \"nome\": \"Frutas secas\",\r\n+    \"ingredientes\": [\r\n+      \"Castanha de caju\",\r\n+      \"Castanha do pará\",\r\n+      \"Uva passa\",\r\n+      \"Damasco\",\r\n+      \"Tâmara\",\r\n+      \"Pistache\",\r\n+      \"Amêndoa\",\r\n+      \"Amendoim\"\r\n+    ],\r\n+    \"imagem\": \"frutas_secas.png\"\r\n   },\r\n   {\r\n-  \"nome\": \"Pães e Massas\",\r\n-  \"ingredientes\": [\r\n-  \"Pão\",\r\n-  \"Pão sírio\",\r\n-  \"Tortilha\",\r\n-  \"Macarrão\",\r\n-  \"Nhoque\",\r\n-  \"Massa de pastel\",\r\n-  \"Massa de lasanha\",\r\n-  \"Biscoito\",\r\n-  \"Broa\"\r\n-  ],\r\n-  \"imagem\": \"paes_e_massas.png\"\r\n+    \"nome\": \"Pães e Massas\",\r\n+    \"ingredientes\": [\r\n+      \"Pão\",\r\n+      \"Pão sírio\",\r\n+      \"Tortilha\",\r\n+      \"Macarrão\",\r\n+      \"Nhoque\",\r\n+      \"Massa de pastel\",\r\n+      \"Massa de lasanha\",\r\n+      \"Biscoito\",\r\n+      \"Broa\"\r\n+    ],\r\n+    \"imagem\": \"paes_e_massas.png\"\r\n   },\r\n   {\r\n-  \"nome\": \"Doces e guloseimas\",\r\n-  \"ingredientes\": [\r\n-  \"Chocolate\",\r\n-  \"Geleia\",\r\n-  \"Goiabada\",\r\n-  \"Caramelo\",\r\n-  \"Chantilly\",\r\n-  \"Cacau em pó\",\r\n-  \"Suspiro\",\r\n-  \"Gelatina\",\r\n-  \"Paçoca\"\r\n-  ],\r\n-  \"imagem\": \"doces_e_guloseimas.png\"\r\n+    \"nome\": \"Doces e guloseimas\",\r\n+    \"ingredientes\": [\r\n+      \"Chocolate\",\r\n+      \"Geleia\",\r\n+      \"Goiabada\",\r\n+      \"Caramelo\",\r\n+      \"Chantilly\",\r\n+      \"Cacau em pó\",\r\n+      \"Suspiro\",\r\n+      \"Gelatina\",\r\n+      \"Paçoca\"\r\n+    ],\r\n+    \"imagem\": \"doces_e_guloseimas.png\"\r\n   }\r\n-  ]\n+]\n\\ No newline at end of file\n"
                }
            ],
            "date": 1745414484676,
            "name": "Commit-0",
            "content": "[\r\n  {\r\n  \"nome\": \"Laticínios e Ovos\",\r\n  \"ingredientes\": [\r\n  \"Ovos\",\r\n  \"Queijo\",\r\n  \"Leite\",\r\n  \"Manteiga\",\r\n  \"Creme de Leite\",\r\n  \"Iogurte\",\r\n  \"Leite Condensado\",\r\n  \"Sorvete\"\r\n  ],\r\n  \"imagem\": \"laticinios_e_ovos.png\"\r\n  },\r\n  {\r\n  \"nome\": \"Farinhas e Fermentos\",\r\n  \"ingredientes\": [\r\n  \"Farinha de trigo\",\r\n  \"Polvilho\",\r\n  \"Farinha de rosca\",\r\n  \"Canjica\",\r\n  \"Farinha de mandioca\",\r\n  \"Fubá\",\r\n  \"Linhaça\",\r\n  \"Fermento químico\"\r\n  ],\r\n  \"imagem\": \"farinhas_e_fermentos.png\"\r\n  },\r\n  {\r\n  \"nome\": \"Temperos e Especiarias\",\r\n  \"ingredientes\": [\r\n  \"Canela\",\r\n  \"Cravo\",\r\n  \"Orégano\",\r\n  \"Noz moscada\",\r\n  \"Tomilho\",\r\n  \"Pimenta do Reino\",\r\n  \"Cominho\"\r\n  ],\r\n  \"imagem\": \"temperos_e_especiarias.png\"\r\n  },\r\n  {\r\n  \"nome\": \"Óleos, Gorduras e Vinagres\",\r\n  \"ingredientes\": [\r\n  \"Vinagre\",\r\n  \"Óleo\",\r\n  \"Dendê\",\r\n  \"Azeite de Oliva\",\r\n  \"Banha\",\r\n  \"Aceto Balsâmico\",\r\n  \"Óleo de coco\"\r\n  ],\r\n  \"imagem\": \"oleos_gorduras_e_vinagres.png\"\r\n  },\r\n  {\r\n  \"nome\": \"Hortaliças e Verduras\",\r\n  \"ingredientes\": [\r\n  \"Cebola\",\r\n  \"Alho\",\r\n  \"Tomate\",\r\n  \"Abóbora\",\r\n  \"Abobrinha\",\r\n  \"Batata\",\r\n  \"Pimentão\",\r\n  \"Espinafre\",\r\n  \"Cenoura\"\r\n  ],\r\n  \"imagem\": \"hortalicas_e_verduras.png\"\r\n  },\r\n  {\r\n  \"nome\": \"Açúcares e Adoçantes\",\r\n  \"ingredientes\": [\r\n  \"Açúcar branco\",\r\n  \"Açúcar mascavo\",\r\n  \"Açúcar cristal\",\r\n  \"Melado\",\r\n  \"Mel\",\r\n  \"Baunilha\",\r\n  \"Glucose\",\r\n  \"Xilito\",\r\n  \"Stevia\"\r\n  ],\r\n  \"imagem\": \"acucares_e_adocantes.png\"\r\n  },\r\n  {\r\n  \"nome\": \"Proteínas Animais\",\r\n  \"ingredientes\": [\r\n  \"Peixe\",\r\n  \"Carne bovina\",\r\n  \"Carne de porco\",\r\n  \"Frango\",\r\n  \"Bacon\",\r\n  \"Salsicha\",\r\n  \"Atum\",\r\n  \"Salmão\",\r\n  \"Presunto\",\r\n  \"Bacalhau\"\r\n  ],\r\n  \"imagem\": \"proteinas_animais.png\"\r\n  },\r\n  {\r\n  \"nome\": \"Grãos, Cereais e Leguminosas\",\r\n  \"ingredientes\": [\r\n  \"Arroz\",\r\n  \"Feijão\",\r\n  \"Aveia\",\r\n  \"Ervilha\",\r\n  \"Lentilha\",\r\n  \"Grão de bico\",\r\n  \"Milho\",\r\n  \"Gergelim\",\r\n  \"Quinoa\"\r\n  ],\r\n  \"imagem\": \"graos_cerais_e_leguminosas.png\"\r\n  },\r\n  {\r\n  \"nome\": \"Frutas frescas\",\r\n  \"ingredientes\": [\r\n  \"Banana\",\r\n  \"Maçã\",\r\n  \"Uva\",\r\n  \"Pera\",\r\n  \"Limão\",\r\n  \"Morango\",\r\n  \"Ameixa\",\r\n  \"Framboesa\",\r\n  \"Acabaxi\"\r\n  ],\r\n  \"imagem\": \"frutas_frescas.png\"\r\n  },\r\n  {\r\n  \"nome\": \"Frutas secas\",\r\n  \"ingredientes\": [\r\n  \"Castanha de caju\",\r\n  \"Castanha do pará\",\r\n  \"Uva passa\",\r\n  \"Damasco\",\r\n  \"Tâmara\",\r\n  \"Pistache\",\r\n  \"Amêndoa\",\r\n  \"Amendoim\"\r\n  ],\r\n  \"imagem\": \"frutas_secas.png\"\r\n  },\r\n  {\r\n  \"nome\": \"Pães e Massas\",\r\n  \"ingredientes\": [\r\n  \"Pão\",\r\n  \"Pão sírio\",\r\n  \"Tortilha\",\r\n  \"Macarrão\",\r\n  \"Nhoque\",\r\n  \"Massa de pastel\",\r\n  \"Massa de lasanha\",\r\n  \"Biscoito\",\r\n  \"Broa\"\r\n  ],\r\n  \"imagem\": \"paes_e_massas.png\"\r\n  },\r\n  {\r\n  \"nome\": \"Doces e guloseimas\",\r\n  \"ingredientes\": [\r\n  \"Chocolate\",\r\n  \"Geleia\",\r\n  \"Goiabada\",\r\n  \"Caramelo\",\r\n  \"Chantilly\",\r\n  \"Cacau em pó\",\r\n  \"Suspiro\",\r\n  \"Gelatina\",\r\n  \"Paçoca\"\r\n  ],\r\n  \"imagem\": \"doces_e_guloseimas.png\"\r\n  }\r\n  ]"
        }
    ]
}